maaranparottakadai/__init__.py
maaranparottakadai/parotta.py
maaranparottakadai-0.1.0.dist-info/LICENSE
maaranparottakadai-0.1.0.dist-info/METADATA
maaranparottakadai-0.1.0.dist-info/WHEEL
maaranparottakadai-0.1.0.dist-info/entry_points.txt
maaranparottakadai-0.1.0.dist-info/top_level.txt
maaranparottakadai-0.1.0.dist-info/RECORD
