Metadata-Version: 2.2
Name: maaranparottakadai
Version: 0.1.0
Summary: A fun Python package about Maaran Parotta Kadai!
Home-page: https://github.com/yourusername/maaranparottakadai
Author: Balamurugan
License: MIT
Classifier: Programming Language :: Python :: 3
Classifier: License :: OSI Approved :: MIT License
Classifier: Operating System :: OS Independent
Requires-Python: >=3.6
License-File: LICENSE
Dynamic: author
Dynamic: classifier
Dynamic: description
Dynamic: description-content-type
Dynamic: home-page
Dynamic: license
Dynamic: requires-python
Dynamic: summary
